<Stats deaths="1" kills="54" player_kills="0" player_projectile_count="0" >
  <death_map>
    <E key="NULL | damage from material: (Vanilla) acid" value="1" >
    </E>
  </death_map>
  <kill_map>
    <E key="acidshooter_weak" value="1" >
    </E>
    <E key="firemage_weak" value="3" >
    </E>
    <E key="fish" value="31" >
    </E>
    <E key="fungus" value="2" >
    </E>
    <E key="longleg" value="1" >
    </E>
    <E key="miner_fire" value="1" >
    </E>
    <E key="miner_weak" value="1" >
    </E>
    <E key="necromancer_shop" value="2" >
    </E>
    <E key="scavenger_smg" value="1" >
    </E>
    <E key="slimeshooter_weak" value="3" >
    </E>
    <E key="thundermage" value="1" >
    </E>
    <E key="zombie_weak" value="7" >
    </E>
  </kill_map>
</Stats>
