<Stats BUILD_NAME="Noita-Build-Jan 25 2025-15:55:41" >
  <stats biomes_visited_with_wands="3" damage_taken="6.853" dead="1" death_count="0" death_pos.x="150.883" death_pos.y="2180.19" enemies_killed="11" gold="115" gold_all="155" gold_infinite="0" healed="0" heart_containers="0" hp="100" items="10" kicks="21" killed_by="(new_enemies) Ärtsylonkero | projectile" killed_by_extra="" places_visited="3" playtime="274.267" playtime_str="0:04:34" projectiles_shot="139" streaks="0" teleports="0" wands_edited="3" world_seed="804110268" >
  </stats>
  <biome_baseline biomes_visited_with_wands="2" damage_taken="2.445" dead="0" death_count="0" death_pos.x="0" death_pos.y="0" enemies_killed="11" gold="4" gold_all="44" gold_infinite="0" healed="0" heart_containers="0" hp="100" items="4" kicks="20" killed_by="" killed_by_extra="" places_visited="2" playtime="194.333" playtime_str="0:03:14" projectiles_shot="135" streaks="0" teleports="0" wands_edited="3" world_seed="804110268" >
  </biome_baseline>
  <item_map>
  </item_map>
  <biomes_visited>
    <E key="$biome_excavationsite" value="1" >
    </E>
    <E key="$biome_holymountain" value="1" >
    </E>
    <E key="Aquifer" value="1" >
    </E>
  </biomes_visited>
</Stats>
