<Stats deaths="26" kills="7" player_kills="0" player_projectile_count="0" >
  <death_map>
    <E key="NULL | $damage_fire" value="2" >
    </E>
    <E key="NULL | damage from material: Cursed rock" value="1" >
    </E>
    <E key="lukki_dark | $damage_curse" value="2" >
    </E>
    <E key="meatmaggot | worm bite" value="1" >
    </E>
    <E key="orb_green | $damage_projectile" value="1" >
    </E>
    <E key="player | $damage_projectile" value="16" >
    </E>
    <E key="player | bzzt!" value="1" >
    </E>
    <E key="rock_curse | $damage_rock_curse" value="1" >
    </E>
    <E key="skullfly | $damage_fire" value="1" >
    </E>
  </death_map>
  <kill_map>
    <E key="lurker" value="1" >
    </E>
    <E key="meatmaggot" value="1" >
    </E>
    <E key="scorpion" value="4" >
    </E>
    <E key="zombie" value="1" >
    </E>
  </kill_map>
</Stats>
